{
  "status": "OPTIMAL",
  "num_vehicles_used": 2,
  "total_distance_meters": 37430.0,
  "total_distance_km": 37.43,
  "total_fixed_cost": 4800.0,
  "total_fuel_cost": 299.44,
  "total_cost": 5099.44,
  "validation": {
    "all_nodes_visited": true,
    "all_routes_valid": true,
    "errors": []
  },
  "routes": [
    {
      "vehicle_id": 1,
      "vehicle_type": "A",
      "route": [
        1,
        2,
        3,
        4,
        5,
        118,
        119,
        122,
        123,
        125,
        124,
        126,
        127,
        130,
        128,
        131,
        132,
        129,
        133,
        134,
        121,
        120,
        117,
        116,
        115,
        113,
        114,
        111,
        112,
        104,
        109,
        110,
        108,
        107,
        106,
        105,
        96,
        98,
        97,
        87,
        88,
        95,
        94,
        93,
        91,
        92,
        90,
        89,
        86,
        85,
        83,
        80,
        79,
        81,
        84,
        82,
        100,
        102,
        99,
        101,
        103,
        78,
        138,
        1
      ],
      "distance_meters": 17187.0,
      "distance_km": 17.187,
      "general_load": 1509.0,
      "recycle_load": 87.0,
      "fixed_cost": 2400.0,
      "fuel_cost": 137.5,
      "total_cost": 2537.5
    },
    {
      "vehicle_id": 2,
      "vehicle_type": "A",
      "route": [
        1,
        13,
        9,
        10,
        8,
        6,
        7,
        15,
        18,
        17,
        30,
        28,
        26,
        25,
        23,
        20,
        19,
        12,
        11,
        135,
        137,
        136,
        21,
        22,
        24,
        41,
        27,
        43,
        40,
        29,
        31,
        39,
        48,
        51,
        52,
        60,
        62,
        64,
        65,
        69,
        70,
        63,
        71,
        75,
        77,
        76,
        74,
        73,
        72,
        68,
        67,
        66,
        56,
        57,
        44,
        42,
        45,
        47,
        46,
        55,
        53,
        54,
        58,
        59,
        61,
        50,
        49,
        38,
        37,
        36,
        33,
        35,
        32,
        34,
        16,
        14,
        138,
        1
      ],
      "distance_meters": 20243.0,
      "distance_km": 20.243,
      "general_load": 1355.0,
      "recycle_load": 92.0,
      "fixed_cost": 2400.0,
      "fuel_cost": 161.94,
      "total_cost": 2561.94
    }
  ],
  "sheet_name": "138"
}